pytheus/__init__.py
pytheus/exceptions.py
pytheus/exposition.py
pytheus/metrics.py
pytheus/middleware.py
pytheus/py.typed
pytheus/registry.py
pytheus/utils.py
pytheus/backends/__init__.py
pytheus/backends/base.py
pytheus/backends/redis.py
pytheus/experimental/__init__.py
pytheus/experimental/adapters.py
pytheus/experimental/compatibility.py
pytheus-0.6.1.dist-info/licenses/LICENSE
pytheus-0.6.1.dist-info/METADATA
pytheus-0.6.1.dist-info/WHEEL
pytheus-0.6.1.dist-info/top_level.txt
pytheus-0.6.1.dist-info/RECORD
