Metadata-Version: 2.4
Name: pytheus
Version: 0.6.1
Summary: playing with metrics
Author-email: Llandy Riveron Del Risco <llandy3d@gmail.com>
Project-URL: Homepage, https://github.com/Llandy3d/pytheus
Project-URL: Documentation, https://pythe.us
Classifier: Programming Language :: Python :: 3
Classifier: Programming Language :: Python :: 3.8
Classifier: Programming Language :: Python :: 3.9
Classifier: Programming Language :: Python :: 3.10
Classifier: Programming Language :: Python :: 3.11
Classifier: Programming Language :: Python :: 3.12
Classifier: Programming Language :: Python :: 3.13
Requires-Python: >=3.8
License-File: LICENSE
Requires-Dist: typing-extensions>=4.0.0
Provides-Extra: test
Requires-Dist: pytest>=7.0.0; extra == "test"
Requires-Dist: pytest-asyncio>=0.21.0; extra == "test"
Requires-Dist: mypy==1.1.1; extra == "test"
Requires-Dist: ruff==0.0.260; extra == "test"
Requires-Dist: black==23.3.0; extra == "test"
Requires-Dist: isort==5.12.0; extra == "test"
Requires-Dist: tox==4.4.11; extra == "test"
Requires-Dist: types-redis==4.6.0.20241004; extra == "test"
Provides-Extra: redis
Requires-Dist: redis>=4.0.0; extra == "redis"
Provides-Extra: prometheus-client
Requires-Dist: prometheus_client>=0.17.1; extra == "prometheus-client"
Provides-Extra: docs
Requires-Dist: mkdocs==1.4.2; extra == "docs"
Requires-Dist: mkdocs-material==9.1.5; extra == "docs"
Dynamic: license-file
